<annotation verified="yes">
	<folder>train2</folder>
	<filename>pill_468.JPG</filename>
	<path>/home/ubuntu/Documents/pill-dataset/train2/pill_468.JPG</path>
	<source>
		<database>Unknown</database>
	</source>
	<size>
		<width>640</width>
		<height>480</height>
		<depth>3</depth>
	</size>
	<segmented>0</segmented>
	<object>
		<name>F</name>
		<pose>Unspecified</pose>
		<truncated>0</truncated>
		<difficult>0</difficult>
		<bndbox>
			<xmin>293</xmin>
			<ymin>52</ymin>
			<xmax>381</xmax>
			<ymax>150</ymax>
		</bndbox>
	</object>
	<object>
		<name>4</name>
		<pose>Unspecified</pose>
		<truncated>0</truncated>
		<difficult>0</difficult>
		<bndbox>
			<xmin>266</xmin>
			<ymin>249</ymin>
			<xmax>327</xmax>
			<ymax>337</ymax>
		</bndbox>
	</object>
	<object>
		<name>8</name>
		<pose>Unspecified</pose>
		<truncated>0</truncated>
		<difficult>0</difficult>
		<bndbox>
			<xmin>334</xmin>
			<ymin>251</ymin>
			<xmax>404</xmax>
			<ymax>338</ymax>
		</bndbox>
	</object>
</annotation>
